LICENSE
MANIFEST.in
README.md
requirements.txt
setup.py
markdown_tags/VERSION
markdown_tags/__init__.py
markdown_tags/markdown_tags.py
markdown_tags.egg-info/PKG-INFO
markdown_tags.egg-info/SOURCES.txt
markdown_tags.egg-info/dependency_links.txt
markdown_tags.egg-info/not-zip-safe
markdown_tags.egg-info/requires.txt
markdown_tags.egg-info/top_level.txt
markdown_tags/reddit_specific/__init__.py
markdown_tags/reddit_specific/reddit_specific.py
markdown_tags/reddit_specific/movies_subreddit/__init__.py
markdown_tags/reddit_specific/movies_subreddit/movies_subreddit.py