Metadata-Version: 1.1
Name: markdown-tags
Version: 0.2.1
Summary: A small library for writing markdown with a tree structure of python objects that you can transform into a markdown snippet(string).
Home-page: http://crouchofthewildtiger.com/
Author: Roman A. Taycher
Author-email: rtaycher1987@gmail.com
License: MIT License
Keywords: markdown tags
Platform: UNKNOWN
Classifier: Development Status :: 3 - Alpha
Classifier: Intended Audience :: Developers
Classifier: License :: OSI Approved :: MIT License
Classifier: Operating System :: OS Independent
Classifier: Topic :: Internet
Classifier: Topic :: Software Development :: Libraries :: Python Modules
